LICENSE
README.md
setup.py
apo/__init__.py
apo.egg-info/PKG-INFO
apo.egg-info/SOURCES.txt
apo.egg-info/dependency_links.txt
apo.egg-info/top_level.txt